dictionary/__init__.py
dictionary/dictionary.py
atakan_saglams_dictionary-2.0.1.dist-info/METADATA
atakan_saglams_dictionary-2.0.1.dist-info/WHEEL
atakan_saglams_dictionary-2.0.1.dist-info/top_level.txt
atakan_saglams_dictionary-2.0.1.dist-info/RECORD
